alphahutch
tests
