Metadata-Version: 2.1
Name: alphahutch
Version: 0.0.3
Summary: Common packages that will be used for alphahutch
Home-page: https://github.com/HutchNunez/alphahutch
Author: Andy Hutchinson
